garb_alarm_clock/MainWindow.py
garb_alarm_clock/__init__.py
garb_alarm_clock/garb.py
garb_alarm_clock-0.2.1.dist-info/licenses/AUTHORS.rst
garb_alarm_clock-0.2.1.dist-info/licenses/LICENSE
garb_alarm_clock-0.2.1.dist-info/METADATA
garb_alarm_clock-0.2.1.dist-info/WHEEL
garb_alarm_clock-0.2.1.dist-info/entry_points.txt
garb_alarm_clock-0.2.1.dist-info/top_level.txt
garb_alarm_clock-0.2.1.dist-info/RECORD
